regexonic/__init__.py
regexonic/core.py
regexonic-0.1.0.dist-info/METADATA
regexonic-0.1.0.dist-info/WHEEL
regexonic-0.1.0.dist-info/licenses/LICENSE
regexonic-0.1.0.dist-info/RECORD
