Metadata-Version: 2.4
Name: regexonic
Version: 0.1.0
Summary: A more pythonic extension of the builtin `re` module.
Project-URL: homepage, https://pypi.org/project/regexonic
Project-URL: repository, https://github.com/harttraveller/regexonic
Project-URL: documentation, https://github.com/harttraveller/regexonic
Author-email: Hart Traveller <ruling_fiction.0b@icloud.com>
License-Expression: MIT
License-File: LICENSE
Requires-Python: >=3.11
